ennio/__init__.py
ennio/app.py
ennio/stack.py
ennio/toolbox.py
ennio/utils.py
ennio-0.1.2.dist-info/LICENSE
ennio-0.1.2.dist-info/METADATA
ennio-0.1.2.dist-info/WHEEL
ennio-0.1.2.dist-info/top_level.txt
ennio-0.1.2.dist-info/RECORD
