Metadata-Version: 2.1
Name: ennio
Version: 0.1.2
Summary: interstack orchestration framework for AWS CloudFormation
Home-page: https://github.com/sportsbet/ennio
Author: Sportsbet
Author-email: engineering@sportsbet.com.au
License: Apache-2.0
Platform: UNKNOWN
Classifier: Development Status :: 4 - Beta
Classifier: License :: OSI Approved :: Apache Software License
Classifier: Programming Language :: Python
Classifier: Programming Language :: Python :: 3
Classifier: Programming Language :: Python :: 3.6
Classifier: Programming Language :: Python :: 3.7
Requires-Dist: PyYAML
Requires-Dist: boto3
Requires-Dist: jinja2
